stackstr/__init__.py
stackstr/deploy.py
stackstr/common/__init__.py
stackstr/common/api.py
stackstr/common/utils.py
stackstr-0.2.0.dist-info/METADATA
stackstr-0.2.0.dist-info/WHEEL
stackstr-0.2.0.dist-info/top_level.txt
stackstr-0.2.0.dist-info/RECORD
