Metadata-Version: 2.1
Name: stackstr
Version: 0.2.0
Summary: A small sdk to deploy your machine learning models right from your notebook
Home-page: https://stackstr.io
Author: StackStr Engineering
Author-email: founders@stackstr.io
License: UNKNOWN
Keywords: stackstr,machine learning,infrastructure
Platform: UNKNOWN
Requires-Dist: certifi
Requires-Dist: chardet
Requires-Dist: idna
Requires-Dist: joblib
Requires-Dist: requests
Requires-Dist: urllib3
